MANIFEST.in
README.rst
setup.cfg
setup.py
versioneer.py
sugartex/__init__.py
sugartex/_version.py
sugartex/kiwi.py
sugartex/pre_sugartex.py
sugartex/sugartex_filter.py
sugartex/sugartex_pandoc_filter.py
sugartex.egg-info/PKG-INFO
sugartex.egg-info/SOURCES.txt
sugartex.egg-info/dependency_links.txt
sugartex.egg-info/entry_points.txt
sugartex.egg-info/requires.txt
sugartex.egg-info/top_level.txt