Metadata-Version: 1.1
Name: sugartex
Version: 0.1.13
Summary: More readable LaTeX language extension and transcompiler to LaTeX
Home-page: https://github.com/kiwi0fruit/sugartex
Author: Peter Zagubisalo
Author-email: peter.zagubisalo@gmail.com
License: MIT
Platform: UNKNOWN
Classifier: Development Status :: 3 - Alpha
Classifier: Intended Audience :: Developers
Classifier: Topic :: Software Development :: Build Tools
Classifier: License :: OSI Approved :: MIT License
Classifier: Programming Language :: Python :: 3
Classifier: Programming Language :: Python :: 3.5
Classifier: Programming Language :: Python :: 3.6
